bahire_hasab/__init__.py
bahire_hasab/__main__.py
bahire_hasab-0.2.8.dist-info/LICENSE
bahire_hasab-0.2.8.dist-info/METADATA
bahire_hasab-0.2.8.dist-info/WHEEL
bahire_hasab-0.2.8.dist-info/entry_points.txt
bahire_hasab-0.2.8.dist-info/top_level.txt
bahire_hasab-0.2.8.dist-info/RECORD
