Metadata-Version: 2.1
Name: bahire-hasab
Version: 0.2.8
Home-page: https://github.com/hunderaweke/bahire-hasab
Author: Hundera Awoke
Author-email: hunderaweke@gmail.com
Keywords: bahire_hasab
License-File: LICENSE
